LICENSE
README.md
pyproject.toml
setup.py
shellmates/__init__.py
shellmates/cli.py
shellmates.egg-info/PKG-INFO
shellmates.egg-info/SOURCES.txt
shellmates.egg-info/dependency_links.txt
shellmates.egg-info/entry_points.txt
shellmates.egg-info/requires.txt
shellmates.egg-info/top_level.txt