Metadata-Version: 2.4
Name: shellmates
Version: 0.1.5
Summary: A terminal based gaming hub.
Author: Edgardo Gutierrez Jr.
Author-email: edgardogutierrezjr@gmail.com
Requires-Python: >=3.8
License-File: LICENSE
Requires-Dist: setuptools>=80.9.0
Requires-Dist: twine>=6.2.0
Dynamic: author
Dynamic: author-email
Dynamic: license-file
Dynamic: requires-python
